{
  "flowSegmentData": {
    "frc": "FRC3",
    "currentSpeed": 37,
    "freeFlowSpeed": 41,
    "currentTravelTime": 328,
    "freeFlowTravelTime": 296,
    "confidence": 1,
    "roadClosure": false,
    "coordinates": {
      "coordinate": [
        {
          "latitude": 43.25827006311848,
          "longitude": 76.8701483069151
        },
        {
          "latitude": 43.25823117867736,
          "longitude": 76.8698157129972
        },
        {
          "latitude": 43.25811983596458,
          "longitude": 76.86920953375972
        },
        {
          "latitude": 43.25805683933948,
          "longitude": 76.8689748404708
        },
        {
          "latitude": 43.25796295471332,
          "longitude": 76.86863017661233
        },
        {
          "latitude": 43.25781272680171,
          "longitude": 76.86815140230306
        },
        {
          "latitude": 43.257580699948996,
          "longitude": 76.86740843040576
        },
        {
          "latitude": 43.257512330910316,
          "longitude": 76.86719385368451
        },
        {
          "latitude": 43.25747747487982,
          "longitude": 76.86708522421935
        },
        {
          "latitude": 43.257423817308734,
          "longitude": 76.86692563278297
        },
        {
          "latitude": 43.25718776006072,
          "longitude": 76.86620948297582
        },
        {
          "latitude": 43.25708453432541,
          "longitude": 76.86589968783449
        },
        {
          "latitude": 43.25700139200332,
          "longitude": 76.86564353687356
        },
        {
          "latitude": 43.25693161829297,
          "longitude": 76.86542896015231
        },
        {
          "latitude": 43.256833702995074,
          "longitude": 76.86512452942907
        },
        {
          "latitude": 43.256734505603205,
          "longitude": 76.86481741649675
        },
        {
          "latitude": 43.256706302992114,
          "longitude": 76.86473426801729
        },
        {
          "latitude": 43.25668890527101,
          "longitude": 76.86467928273248
        },
        {
          "latitude": 43.25654941809905,
          "longitude": 76.86436948759115
        },
        {
          "latitude": 43.25639656176774,
          "longitude": 76.86404091698677
        },
        {
          "latitude": 43.25614169862091,
          "longitude": 76.8636359034254
        },
        {
          "latitude": 43.25591912744099,
          "longitude": 76.86330465061201
        },
        {
          "latitude": 43.25575412145807,
          "longitude": 76.86306995732315
        },
        {
          "latitude": 43.25567366332867,
          "longitude": 76.86295864564903
        },
        {
          "latitude": 43.255582461041236,
          "longitude": 76.8628205118847
        },
        {
          "latitude": 43.25543766034183,
          "longitude": 76.86261666399952
        },
        {
          "latitude": 43.25466786669455,
          "longitude": 76.86156389696094
        },
        {
          "latitude": 43.254065699361334,
          "longitude": 76.86072838885258
        },
        {
          "latitude": 43.25391283679547,
          "longitude": 76.86050978881786
        },
        {
          "latitude": 43.25341792329213,
          "longitude": 76.85979766232424
        },
        {
          "latitude": 43.25340186768618,
          "longitude": 76.85977486354761
        },
        {
          "latitude": 43.25312690714633,
          "longitude": 76.85935375673216
        },
        {
          "latitude": 43.25288417895965,
          "longitude": 76.85897556526095
        },
        {
          "latitude": 43.25269907975263,
          "longitude": 76.85865101797009
        },
        {
          "latitude": 43.25254218453571,
          "longitude": 76.85829026085753
        },
        {
          "latitude": 43.25248858366468,
          "longitude": 76.85817358476532
        },
        {
          "latitude": 43.252398719683924,
          "longitude": 76.85797644240267
        },
        {
          "latitude": 43.252248478045,
          "longitude": 76.85760897976758
        },
        {
          "latitude": 43.252236451372,
          "longitude": 76.85756606442334
        },
        {
          "latitude": 43.25211972536629,
          "longitude": 76.85718116742959
        },
        {
          "latitude": 43.25190654110069,
          "longitude": 76.85641003233764
        },
        {
          "latitude": 43.25186765259604,
          "longitude": 76.8562531231102
        },
        {
          "latitude": 43.25155648261516,
          "longitude": 76.85501394254504
        },
        {
          "latitude": 43.25145190423637,
          "longitude": 76.854575401371
        },
        {
          "latitude": 43.25127351618462,
          "longitude": 76.85382706505567
        },
        {
          "latitude": 43.25103480993182,
          "longitude": 76.85289499742282
        },
        {
          "latitude": 43.25098786222371,
          "longitude": 76.85268310291053
        },
        {
          "latitude": 43.250932855825184,
          "longitude": 76.85241354090454
        },
        {
          "latitude": 43.25075989975567,
          "longitude": 76.8515659628556
        },
        {
          "latitude": 43.2506069678414,
          "longitude": 76.8509128449603
        },
        {
          "latitude": 43.25038169019035,
          "longitude": 76.85001028162662
        },
        {
          "latitude": 43.249953843512,
          "longitude": 76.84838754517222
        },
        {
          "latitude": 43.249842546715946,
          "longitude": 76.84796643835676
        },
        {
          "latitude": 43.24979425495454,
          "longitude": 76.84778538924826
        },
        {
          "latitude": 43.24975805137129,
          "longitude": 76.84764993769295
        },
        {
          "latitude": 43.249672212772474,
          "longitude": 76.84732270819308
        },
        {
          "latitude": 43.249350347475634,
          "longitude": 76.84605938774678
        },
        {
          "latitude": 43.24930077323095,
          "longitude": 76.84583408218941
        },
        {
          "latitude": 43.249247108455094,
          "longitude": 76.8456168232592
        },
        {
          "latitude": 43.24914386925954,
          "longitude": 76.84530568701337
        },
        {
          "latitude": 43.24905937294563,
          "longitude": 76.84512061459128
        },
        {
          "latitude": 43.2489869038316,
          "longitude": 76.84495968205039
        },
        {
          "latitude": 43.2486368896178,
          "longitude": 76.84414965492772
        },
        {
          "latitude": 43.24852290409083,
          "longitude": 76.8439149616388
        },
        {
          "latitude": 43.248296275564215,
          "longitude": 76.84344557506114
        },
        {
          "latitude": 43.24815139648726,
          "longitude": 76.84314650875592
        },
        {
          "latitude": 43.24791267799812,
          "longitude": 76.842639571252
        },
        {
          "latitude": 43.24768604720111,
          "longitude": 76.84211519938941
        },
        {
          "latitude": 43.24761901023585,
          "longitude": 76.84196097237106
        },
        {
          "latitude": 43.24720457606595,
          "longitude": 76.84100610596153
        },
        {
          "latitude": 43.246937707785584,
          "longitude": 76.84035969358877
        },
        {
          "latitude": 43.24689747291022,
          "longitude": 76.84026045185522
        },
        {
          "latitude": 43.246650751340866,
          "longitude": 76.83961135727344
        },
        {
          "latitude": 43.24651930041594,
          "longitude": 76.83925060016088
        },
        {
          "latitude": 43.24634358433797,
          "longitude": 76.83876109701549
        },
        {
          "latitude": 43.246229594519434,
          "longitude": 76.83842582088857
        },
        {
          "latitude": 43.24602579215914,
          "longitude": 76.83782634717363
        },
        {
          "latitude": 43.245965408404956,
          "longitude": 76.8376332281245
        },
        {
          "latitude": 43.245918456789326,
          "longitude": 76.83749107104666
        },
        {
          "latitude": 43.24584738821515,
          "longitude": 76.8372657654894
        },
        {
          "latitude": 43.2458340170566,
          "longitude": 76.83722419124962
        },
        {
          "latitude": 43.24574548648088,
          "longitude": 76.83694792372103
        },
        {
          "latitude": 43.24568778889845,
          "longitude": 76.83676687461252
        },
        {
          "latitude": 43.24544777858024,
          "longitude": 76.83597025853487
        },
        {
          "latitude": 43.245093714316184,
          "longitude": 76.83465463501278
        },
        {
          "latitude": 43.24506153765493,
          "longitude": 76.83453393560711
        },
        {
          "latitude": 43.24475979667619,
          "longitude": 76.83339936119353
        }
      ]
    },
    "@version": "traffic-service-flow 1.0.136"
  }
}